pybuilder_docker_build/__init__.py
pybuilder_docker_build/util.py
pybuilder_docker_build-0.5.1.dist-info/METADATA
pybuilder_docker_build-0.5.1.dist-info/WHEEL
pybuilder_docker_build-0.5.1.dist-info/namespace_packages.txt
pybuilder_docker_build-0.5.1.dist-info/top_level.txt
pybuilder_docker_build-0.5.1.dist-info/zip-safe
pybuilder_docker_build-0.5.1.dist-info/RECORD
