Metadata-Version: 2.1
Name: pybuilder-docker-build
Version: 0.5.1
Summary: A Docker build plugin for PyBuilder
Home-page: https://github.com/jlsheehan/pybuilder-docker-build
Author: Jeffrey Sheehan
Author-email: jeff.sheehan7@gmail.com
Maintainer: 
Maintainer-email: 
License: MIT License
Classifier: Development Status :: 3 - Alpha
Classifier: Programming Language :: Python
Requires-Dist: docker
